djstart/__init__.py
djstart/main.py
djstart/write.py
djstart/templates/settings.py.j2
djstart-0.1.0.dist-info/licenses/LICENSE
djstart-0.1.0.dist-info/METADATA
djstart-0.1.0.dist-info/WHEEL
djstart-0.1.0.dist-info/entry_points.txt
djstart-0.1.0.dist-info/top_level.txt
djstart-0.1.0.dist-info/RECORD
